baratine/__init__.py
baratine/baratine_client.py
baratine/exception.py
baratine/jamp.py
baratine/jamp_client.py
baratine/transport.py
baratine-0.9.0.dist-info/DESCRIPTION.rst
baratine-0.9.0.dist-info/METADATA
baratine-0.9.0.dist-info/metadata.json
baratine-0.9.0.dist-info/RECORD
baratine-0.9.0.dist-info/top_level.txt
baratine-0.9.0.dist-info/WHEEL
